{
    "env": {
        "name": "LunarLanderContinuous-v2",
        "obs_clip": false,
        "obs_norm": true,
        "obs_noise": 0.0
    },
    "name_env": true,
    "name_agent": true,
    "name_tag": "",
    "name_time": false,
    "n_avg": 3,
    "n_stp_max": 1000000,
    "trainer": {
        "style": "td",
        "mem_size": 1000000,
        "btc_size": 128,
        "n_stp_unroll": 50,
        "render_every": 50000
    },
    "agent": {
        "type": "ddpg",
        "gamma": 0.99,
        "rho": 0.995,
        "n_warmup": 10000,
        "n_filling": 1000,
        "sigma": 0.1,
        "policy": {
            "type": "deterministic",
            "network": {
                "type": "fc",
                "trunk": {
                    "arch": [256,256],
                    "actv": "relu"
                },
                "heads": {
                    "nb": 1,
                    "arch": [[]],
                    "actv": ["relu"],
                    "final": ["tanh"]
                }
            },
            "optimizer": {
                "type": "adam",
                "lr": 5.0e-4,
                "grd_clip": null
            },
            "loss": {
                "type": "q_pol"
            }
        },
        "value": {
            "type": "q_value",
            "network": {
                "type": "fc",
                "trunk": {
                    "arch": [256,256],
                    "actv": "relu"
                },
                "heads": {
                    "nb": 1,
                    "arch": [[]],
                    "actv": ["relu"],
                    "final": ["linear"]
                }
            },
            "optimizer": {
                "type": "adam",
                "lr": 5.0e-4,
                "grd_clip": null
            },
            "loss": {
                "type": "mse_ddpg"
            }
        },
        "termination": {
            "type": "bootstrap"
        }
    }
}
